{
  "program": {
    "id": "prog_leangain_4week_01",
    "title": "4-Week Lean Gain",
    "subtitle": "Muscle Gain • Strength Building",
    "category": "strength",
    "coverImageURL": "leangain_4week_cover.jpg",
    "totalDays": 28,
    "isActive": true
  },
  "workoutDays": [
    {
      "id": "week1_day1_upper",
      "programId": "prog_leangain_4week_01",
      "dayNumber": 1,
      "title": "Upper Body Strength",
      "description": "Focus on chest, shoulders, and back with heavy compound movements.",
      "estimatedDurationMinutes": 60,
      "isRestDay": false
    },
    {
      "id": "week1_day2_lower",
      "programId": "prog_leangain_4week_01",
      "dayNumber": 2,
      "title": "Lower Body Power",
      "description": "Build leg strength with squats, deadlifts, and accessory work.",
      "estimatedDurationMinutes": 65,
      "isRestDay": false
    }
  ],
  "exercises": [
    {
      "id": "ex_upper_bench_press",
      "workoutDayId": "week1_day1_upper",
      "name": "Barbell Bench Press",
      "order": 1,
      "equipment": "barbell",
      "restSeconds": 180,
      "targetMuscleGroups": ["chest", "arms"      ],
      "videoLink": "https://www.youtube.com/watch?v=k9MY1ijAvGo",
      "sets": [
        {"id": "ex_upper_bench_press_s1", "setNumber": 1, "targetReps": 5, "targetWeight": null},
        {"id": "ex_upper_bench_press_s2", "setNumber": 2, "targetReps": 5, "targetWeight": null},
        {"id": "ex_upper_bench_press_s3", "setNumber": 3, "targetReps": 5, "targetWeight": null},
        {"id": "ex_upper_bench_press_s4", "setNumber": 4, "targetReps": 5, "targetWeight": null}
      ]
    },
    {
      "id": "ex_upper_overhead_press",
      "workoutDayId": "week1_day1_upper",
      "name": "Overhead Press",
      "order": 2,
      "equipment": "barbell",
      "restSeconds": 120,
      "targetMuscleGroups": ["shoulders", "arms"      ],
      "videoLink": "https://www.youtube.com/watch?v=k9MY1ijAvGo",
      "sets": [
        {"id": "ex_upper_overhead_press_s1", "setNumber": 1, "targetReps": 6, "targetWeight": null},
        {"id": "ex_upper_overhead_press_s2", "setNumber": 2, "targetReps": 6, "targetWeight": null},
        {"id": "ex_upper_overhead_press_s3", "setNumber": 3, "targetReps": 6, "targetWeight": null}
      ]
    },
    {
      "id": "ex_upper_bent_row",
      "workoutDayId": "week1_day1_upper",
      "name": "Bent-Over Barbell Row",
      "order": 3,
      "equipment": "barbell",
      "restSeconds": 120,
      "targetMuscleGroups": ["back", "arms"      ],
      "videoLink": "https://www.youtube.com/watch?v=k9MY1ijAvGo",
      "sets": [
        {"id": "ex_upper_bent_row_s1", "setNumber": 1, "targetReps": 8, "targetWeight": null},
        {"id": "ex_upper_bent_row_s2", "setNumber": 2, "targetReps": 8, "targetWeight": null},
        {"id": "ex_upper_bent_row_s3", "setNumber": 3, "targetReps": 8, "targetWeight": null}
      ]
    },
    {
      "id": "ex_upper_pullups",
      "workoutDayId": "week1_day1_upper",
      "name": "Pull-Ups",
      "order": 4,
      "equipment": "bodyweight",
      "restSeconds": 90,
      "targetMuscleGroups": ["back", "arms"      ],
      "videoLink": "https://www.youtube.com/watch?v=k9MY1ijAvGo",
      "sets": [
        {"id": "ex_upper_pullups_s1", "setNumber": 1, "targetReps": 8, "targetWeight": null},
        {"id": "ex_upper_pullups_s2", "setNumber": 2, "targetReps": 8, "targetWeight": null},
        {"id": "ex_upper_pullups_s3", "setNumber": 3, "targetReps": 8, "targetWeight": null}
      ]
    },
    {
      "id": "ex_lower_squat",
      "workoutDayId": "week1_day2_lower",
      "name": "Back Squat",
      "order": 1,
      "equipment": "barbell",
      "restSeconds": 180,
      "targetMuscleGroups": ["legs", "core"      ],
      "videoLink": "https://www.youtube.com/watch?v=k9MY1ijAvGo",
      "sets": [
        {"id": "ex_lower_squat_s1", "setNumber": 1, "targetReps": 5, "targetWeight": null},
        {"id": "ex_lower_squat_s2", "setNumber": 2, "targetReps": 5, "targetWeight": null},
        {"id": "ex_lower_squat_s3", "setNumber": 3, "targetReps": 5, "targetWeight": null},
        {"id": "ex_lower_squat_s4", "setNumber": 4, "targetReps": 5, "targetWeight": null}
      ]
    },
    {
      "id": "ex_lower_deadlift",
      "workoutDayId": "week1_day2_lower",
      "name": "Romanian Deadlift",
      "order": 2,
      "equipment": "barbell",
      "restSeconds": 180,
      "targetMuscleGroups": ["legs", "back"      ],
      "videoLink": "https://www.youtube.com/watch?v=k9MY1ijAvGo",
      "sets": [
        {"id": "ex_lower_deadlift_s1", "setNumber": 1, "targetReps": 6, "targetWeight": null},
        {"id": "ex_lower_deadlift_s2", "setNumber": 2, "targetReps": 6, "targetWeight": null},
        {"id": "ex_lower_deadlift_s3", "setNumber": 3, "targetReps": 6, "targetWeight": null}
      ]
    },
    {
      "id": "ex_lower_leg_press",
      "workoutDayId": "week1_day2_lower",
      "name": "Leg Press",
      "order": 3,
      "equipment": "machine",
      "restSeconds": 120,
      "targetMuscleGroups": ["legs"      ],
      "videoLink": "https://www.youtube.com/watch?v=k9MY1ijAvGo",
      "sets": [
        {"id": "ex_lower_leg_press_s1", "setNumber": 1, "targetReps": 10, "targetWeight": null},
        {"id": "ex_lower_leg_press_s2", "setNumber": 2, "targetReps": 10, "targetWeight": null},
        {"id": "ex_lower_leg_press_s3", "setNumber": 3, "targetReps": 10, "targetWeight": null}
      ]
    },
    {
      "id": "ex_lower_leg_curl",
      "workoutDayId": "week1_day2_lower",
      "name": "Leg Curl",
      "order": 4,
      "equipment": "machine",
      "restSeconds": 90,
      "targetMuscleGroups": ["legs"      ],
      "videoLink": "https://www.youtube.com/watch?v=k9MY1ijAvGo",
      "sets": [
        {"id": "ex_lower_leg_curl_s1", "setNumber": 1, "targetReps": 12, "targetWeight": null},
        {"id": "ex_lower_leg_curl_s2", "setNumber": 2, "targetReps": 12, "targetWeight": null},
        {"id": "ex_lower_leg_curl_s3", "setNumber": 3, "targetReps": 12, "targetWeight": null}
      ]
    },
    {
      "id": "ex_push_incline_db",
      "workoutDayId": "week1_day4_push",
      "name": "Incline Dumbbell Press",
      "order": 1,
      "equipment": "dumbbell",
      "restSeconds": 120,
      "targetMuscleGroups": ["chest", "shoulders"      ],
      "videoLink": "https://www.youtube.com/watch?v=k9MY1ijAvGo",
      "sets": [
        {"id": "ex_push_incline_db_s1", "setNumber": 1, "targetReps": 8, "targetWeight": null},
        {"id": "ex_push_incline_db_s2", "setNumber": 2, "targetReps": 8, "targetWeight": null},
        {"id": "ex_push_incline_db_s3", "setNumber": 3, "targetReps": 8, "targetWeight": null},
        {"id": "ex_push_incline_db_s4", "setNumber": 4, "targetReps": 8, "targetWeight": null}
      ]
    },
    {
      "id": "ex_push_shoulder_press",
      "workoutDayId": "week1_day4_push",
      "name": "Dumbbell Shoulder Press",
      "order": 2,
      "equipment": "dumbbell",
      "restSeconds": 90,
      "targetMuscleGroups": ["shoulders", "arms"      ],
      "videoLink": "https://www.youtube.com/watch?v=k9MY1ijAvGo",
      "sets": [
        {"id": "ex_push_shoulder_press_s1", "setNumber": 1, "targetReps": 10, "targetWeight": null},
        {"id": "ex_push_shoulder_press_s2", "setNumber": 2, "targetReps": 10, "targetWeight": null},
        {"id": "ex_push_shoulder_press_s3", "setNumber": 3, "targetReps": 10, "targetWeight": null}
      ]
    },
    {
      "id": "ex_push_triceps",
      "workoutDayId": "week1_day4_push",
      "name": "Close-Grip Bench Press",
      "order": 3,
      "equipment": "barbell",
      "restSeconds": 90,
      "targetMuscleGroups": ["arms"      ],
      "videoLink": "https://www.youtube.com/watch?v=k9MY1ijAvGo",
      "sets": [
        {"id": "ex_push_triceps_s1", "setNumber": 1, "targetReps": 8, "targetWeight": null},
        {"id": "ex_push_triceps_s2", "setNumber": 2, "targetReps": 8, "targetWeight": null},
        {"id": "ex_push_triceps_s3", "setNumber": 3, "targetReps": 8, "targetWeight": null}
      ]
    },
    {
      "id": "ex_push_lateral_raise",
      "workoutDayId": "week1_day4_push",
      "name": "Lateral Raise",
      "order": 4,
      "equipment": "dumbbell",
      "restSeconds": 60,
      "targetMuscleGroups": ["shoulders"      ],
      "videoLink": "https://www.youtube.com/watch?v=k9MY1ijAvGo",
      "sets": [
        {"id": "ex_push_lateral_raise_s1", "setNumber": 1, "targetReps": 12, "targetWeight": null},
        {"id": "ex_push_lateral_raise_s2", "setNumber": 2, "targetReps": 12, "targetWeight": null},
        {"id": "ex_push_lateral_raise_s3", "setNumber": 3, "targetReps": 12, "targetWeight": null}
      ]
    },
    {
      "id": "ex_pull_pulldown",
      "workoutDayId": "week1_day5_pull",
      "name": "Wide-Grip Lat Pulldown",
      "order": 1,
      "equipment": "machine",
      "restSeconds": 120,
      "targetMuscleGroups": ["back"      ],
      "videoLink": "https://www.youtube.com/watch?v=k9MY1ijAvGo",
      "sets": [
        {"id": "ex_pull_pulldown_s1", "setNumber": 1, "targetReps": 8, "targetWeight": null},
        {"id": "ex_pull_pulldown_s2", "setNumber": 2, "targetReps": 8, "targetWeight": null},
        {"id": "ex_pull_pulldown_s3", "setNumber": 3, "targetReps": 8, "targetWeight": null},
        {"id": "ex_pull_pulldown_s4", "setNumber": 4, "targetReps": 8, "targetWeight": null}
      ]
    },
    {
      "id": "ex_pull_cable_row",
      "workoutDayId": "week1_day5_pull",
      "name": "Seated Cable Row",
      "order": 2,
      "equipment": "machine",
      "restSeconds": 90,
      "targetMuscleGroups": ["back"      ],
      "videoLink": "https://www.youtube.com/watch?v=k9MY1ijAvGo",
      "sets": [
        {"id": "ex_pull_cable_row_s1", "setNumber": 1, "targetReps": 10, "targetWeight": null},
        {"id": "ex_pull_cable_row_s2", "setNumber": 2, "targetReps": 10, "targetWeight": null},
        {"id": "ex_pull_cable_row_s3", "setNumber": 3, "targetReps": 10, "targetWeight": null}
      ]
    },
    {
      "id": "ex_pull_face_pull",
      "workoutDayId": "week1_day5_pull",
      "name": "Face Pull",
      "order": 3,
      "equipment": "machine",
      "restSeconds": 60,
      "targetMuscleGroups": ["shoulders", "back"      ],
      "videoLink": "https://www.youtube.com/watch?v=k9MY1ijAvGo",
      "sets": [
        {"id": "ex_pull_face_pull_s1", "setNumber": 1, "targetReps": 15, "targetWeight": null},
        {"id": "ex_pull_face_pull_s2", "setNumber": 2, "targetReps": 15, "targetWeight": null},
        {"id": "ex_pull_face_pull_s3", "setNumber": 3, "targetReps": 15, "targetWeight": null}
      ]
    },
    {
      "id": "ex_pull_barbell_curl",
      "workoutDayId": "week1_day5_pull",
      "name": "Barbell Biceps Curl",
      "order": 4,
      "equipment": "barbell",
      "restSeconds": 60,
      "targetMuscleGroups": ["arms"      ],
      "videoLink": "https://www.youtube.com/watch?v=k9MY1ijAvGo",
      "sets": [
        {"id": "ex_pull_barbell_curl_s1", "setNumber": 1, "targetReps": 10, "targetWeight": null},
        {"id": "ex_pull_barbell_curl_s2", "setNumber": 2, "targetReps": 10, "targetWeight": null},
        {"id": "ex_pull_barbell_curl_s3", "setNumber": 3, "targetReps": 10, "targetWeight": null}
      ]
    },
    {
      "id": "ex_legs_front_squat",
      "workoutDayId": "week1_day6_legs",
      "name": "Front Squat",
      "order": 1,
      "equipment": "barbell",
      "restSeconds": 150,
      "targetMuscleGroups": ["legs", "core"      ],
      "videoLink": "https://www.youtube.com/watch?v=k9MY1ijAvGo",
      "sets": [
        {"id": "ex_legs_front_squat_s1", "setNumber": 1, "targetReps": 6, "targetWeight": null},
        {"id": "ex_legs_front_squat_s2", "setNumber": 2, "targetReps": 6, "targetWeight": null},
        {"id": "ex_legs_front_squat_s3", "setNumber": 3, "targetReps": 6, "targetWeight": null}
      ]
    },
    {
      "id": "ex_legs_bulgarian_split",
      "workoutDayId": "week1_day6_legs",
      "name": "Bulgarian Split Squat",
      "order": 2,
      "equipment": "dumbbell",
      "restSeconds": 90,
      "targetMuscleGroups": ["legs"      ],
      "videoLink": "https://www.youtube.com/watch?v=k9MY1ijAvGo",
      "sets": [
        {"id": "ex_legs_bulgarian_split_s1", "setNumber": 1, "targetReps": 10, "targetWeight": null},
        {"id": "ex_legs_bulgarian_split_s2", "setNumber": 2, "targetReps": 10, "targetWeight": null},
        {"id": "ex_legs_bulgarian_split_s3", "setNumber": 3, "targetReps": 10, "targetWeight": null}
      ]
    },
    {
      "id": "ex_legs_leg_extension",
      "workoutDayId": "week1_day6_legs",
      "name": "Leg Extension",
      "order": 3,
      "equipment": "machine",
      "restSeconds": 60,
      "targetMuscleGroups": ["legs"      ],
      "videoLink": "https://www.youtube.com/watch?v=k9MY1ijAvGo",
      "sets": [
        {"id": "ex_legs_leg_extension_s1", "setNumber": 1, "targetReps": 12, "targetWeight": null},
        {"id": "ex_legs_leg_extension_s2", "setNumber": 2, "targetReps": 12, "targetWeight": null},
        {"id": "ex_legs_leg_extension_s3", "setNumber": 3, "targetReps": 12, "targetWeight": null}
      ]
    },
    {
      "id": "ex_legs_calf_raise",
      "workoutDayId": "week1_day6_legs",
      "name": "Standing Calf Raise",
      "order": 4,
      "equipment": "machine",
      "restSeconds": 60,
      "targetMuscleGroups": ["legs"      ],
      "videoLink": "https://www.youtube.com/watch?v=k9MY1ijAvGo",
      "sets": [
        {"id": "ex_legs_calf_raise_s1", "setNumber": 1, "targetReps": 15, "targetWeight": null},
        {"id": "ex_legs_calf_raise_s2", "setNumber": 2, "targetReps": 15, "targetWeight": null},
        {"id": "ex_legs_calf_raise_s3", "setNumber": 3, "targetReps": 15, "targetWeight": null}
      ]
    }
  ]
}
